emcache/__init__.py
emcache/_address.py
emcache/autobatching.py
emcache/base.py
emcache/client.py
emcache/client_errors.py
emcache/cluster.py
emcache/connection_pool.py
emcache/default_values.py
emcache/node.py
emcache/protocol.py
emcache/py.typed
emcache/timeout.py
emcache/version.py
emcache/_cython/cyemcache.cpython-313-aarch64-linux-gnu.so
emcache-1.3.3.dist-info/METADATA
emcache-1.3.3.dist-info/WHEEL
emcache-1.3.3.dist-info/top_level.txt
emcache-1.3.3.dist-info/RECORD
emcache-1.3.3.dist-info/licenses/LICENSE.txt
