Metadata-Version: 2.4
Name: emcache
Version: 1.3.3
Summary: A high performance asynchronous Python client for Memcached with full batteries included
Home-page: http://github.com/emcache/emcache
Author: Pau Freixes
Author-email: pfreixes@gmail.com
Platform: *nix
Classifier: Development Status :: 4 - Beta
Classifier: Programming Language :: Python :: 3 :: Only
Classifier: Programming Language :: Python :: 3.8
Classifier: Programming Language :: Python :: 3.9
Classifier: Programming Language :: Python :: 3.10
Classifier: Programming Language :: Python :: 3.11
Classifier: Programming Language :: Python :: 3.12
Classifier: Programming Language :: Python :: 3.13
Classifier: Programming Language :: Python :: 3.14
Classifier: License :: OSI Approved :: MIT License
Classifier: Intended Audience :: Developers
Requires-Python: >=3.8
License-File: LICENSE.txt
Provides-Extra: dev
Requires-Dist: Cython==3.2.4; extra == "dev"
Requires-Dist: pytest==8.2.2; extra == "dev"
Requires-Dist: pytest-mock==3.14.0; extra == "dev"
Requires-Dist: pytest-asyncio==0.23.8; extra == "dev"
Requires-Dist: coverage==7.5.3; extra == "dev"
Requires-Dist: black==24.4.2; extra == "dev"
Requires-Dist: isort==5.13.2; extra == "dev"
Requires-Dist: flake8==7.0.0; extra == "dev"
Dynamic: author
Dynamic: author-email
Dynamic: classifier
Dynamic: description
Dynamic: home-page
Dynamic: license-file
Dynamic: platform
Dynamic: provides-extra
Dynamic: summary
